{
  "as_of": "2026-06-24 10:23 KST",
  "sources": [
    "https://www.hankyung.com/koreamarket/news/all-news",
    "https://www.hankyung.com/globalmarket",
    "https://datacenter.hankyung.com/"
  ],
  "headline": "반도체주 차익실현 쏟아져...美 유통·바이오 순환매 주목",
  "us_market_snapshot": [],
  "themes": [
    {
      "title": "반도체주 차익실현 쏟아져...美 유통·바이오 순환매 주목",
      "summary": "",
      "url": "https://www.hankyung.com/article/202606244035i"
    },
    {
      "title": "13% 폭락한 마이크론, 머스크 저격한 손정의…\"건강한 조정\"이라는 월가 [김현석의 월스트리트나우]",
      "summary": "",
      "url": "https://www.hankyung.com/article/202606243956i"
    },
    {
      "title": "루비오 美국무 \"이란, 호르무즈 통행료 못 걷어…국제법 위반”",
      "summary": "",
      "url": "https://www.hankyung.com/article/2026062440677"
    },
    {
      "title": "호르무즈 긴장 완화 기대감…국제유가, 넉달 만에 최저치",
      "summary": "",
      "url": "https://www.hankyung.com/article/2026062440097"
    }
  ],
  "today_kr_focus": [
    "한국투자액셀러레이터, 스타트업 투자 프로그램 '바른동행' 참가사 모집 (2026-06-24 10:18)",
    "투자경고 지정에도…삼전·닉스 공장부지 기대감에 '上' 찍은 종목 (2026-06-24 09:33)",
    "클로봇, 두산로지스틱스솔루션 인수 소식에 12% 급등 (2026-06-24 09:27)"
  ],
  "carousel_implications": {
    "regime": "美 증시 조정 — 위험회피 분위기 (가설)",
    "axes": [
      {
        "axis": "반도체 회전축",
        "view": "美 반도체 지수 -7.87% 조정. 한국 반도체(삼성·하이닉스) 동조 가능성 큼. 저점 매수 진입 검토 — 확신은 합의 시그널과 교차검증 필요.",
        "confidence": "중 — 백테스트 미검증",
        "trigger_metric": "美 반도체 지수",
        "trigger_value": "-7.87%"
      }
    ],
    "note": "★ 모든 함의는 미검증 가설. 백테스트 alpha 확인 전 매매 직접 사용 금지."
  },
  "macro": {
    "collected_at": "2026-06-24T10:23:33.325212+09:00",
    "source": "datacenter.hankyung.com",
    "categories": {
      "major-indices": {
        "label": "한경 데이터센터 해외지수",
        "items": [
          {
            "name": "나스닥",
            "symbol": "NASDAQ",
            "close": "25,587.04",
            "chg": "579.56",
            "chg_pct": "-2.21%"
          },
          {
            "name": "다우존스",
            "symbol": "DJIA",
            "close": "51,666.84",
            "chg": "45.87",
            "chg_pct": "-0.09%"
          },
          {
            "name": "S&P 500",
            "symbol": "SP500",
            "close": "7,365.46",
            "chg": "107.33",
            "chg_pct": "-1.44%"
          },
          {
            "name": "반도체",
            "symbol": "PSEMICON",
            "close": "13,482.51",
            "chg": "1,152.21",
            "chg_pct": "-7.87%"
          },
          {
            "name": "NIKKEI 225",
            "symbol": "NIKKEI",
            "close": "69,788.38",
            "chg": "2,565.58",
            "chg_pct": "-3.55%"
          },
          {
            "name": "대만",
            "symbol": "WEIGHT",
            "close": "47,100.65",
            "chg": "640.86",
            "chg_pct": "-1.34%"
          },
          {
            "name": "독일",
            "symbol": "DAX",
            "close": "24,893.58",
            "chg": "246.11",
            "chg_pct": "-0.98%"
          },
          {
            "name": "홍콩",
            "symbol": "HANGSE",
            "close": "23,336.28",
            "chg": "432.24",
            "chg_pct": "-1.82%"
          }
        ]
      },
      "currencies": {
        "label": "한경 데이터센터 외환",
        "items": [
          {
            "name": "미국",
            "symbol": "USDKRW",
            "close": "1,535.89",
            "chg": "2.63",
            "chg_pct": "+0.17%"
          },
          {
            "name": "유로",
            "symbol": "EURKRW",
            "close": "1,746.78",
            "chg": "1.15",
            "chg_pct": "+0.07%"
          },
          {
            "name": "일본",
            "symbol": "JPYKRW",
            "close": "950.39",
            "chg": "1.31",
            "chg_pct": "+0.14%"
          },
          {
            "name": "중국",
            "symbol": "CNYKRW",
            "close": "226.18",
            "chg": "0.15",
            "chg_pct": "-0.07%"
          }
        ]
      },
      "commodities": {
        "label": "한경 데이터센터 원자재",
        "items": [
          {
            "name": "브렌트",
            "symbol": "BRENTF",
            "close": "76.80",
            "chg": "0.72",
            "chg_pct": "-0.93%"
          },
          {
            "name": "두바이유 현물",
            "symbol": "DUBAIF",
            "close": "71.77",
            "chg": "1.10",
            "chg_pct": "-1.51%"
          },
          {
            "name": "니켈",
            "symbol": "LMENIC",
            "close": "17,105.00",
            "chg": "535.00",
            "chg_pct": "-3.03%"
          },
          {
            "name": "알루미늄 H/G 캐시",
            "symbol": "LMEALC",
            "close": "3,263.50",
            "chg": "141.50",
            "chg_pct": "-4.16%"
          },
          {
            "name": "전기동",
            "symbol": "LMECOC",
            "close": "13,334.00",
            "chg": "308.00",
            "chg_pct": "-2.26%"
          },
          {
            "name": "전기동 3M",
            "symbol": "LMECOF",
            "close": "13,395.00",
            "chg": "317.00",
            "chg_pct": "-2.31%"
          }
        ]
      },
      "rates-bonds": {
        "label": "한경 데이터센터 채권금리",
        "items": [
          {
            "name": "국고10년",
            "symbol": "KR10Y",
            "close": "4.17",
            "chg": "0.02",
            "chg_pct": "-0.52%"
          },
          {
            "name": "국고3년",
            "symbol": "KR3Y",
            "close": "3.77",
            "chg": "0.04",
            "chg_pct": "-1.08%"
          },
          {
            "name": "미국 국채 10년",
            "symbol": "US10YY",
            "close": "4.50",
            "chg": "0.01",
            "chg_pct": "-0.22%"
          },
          {
            "name": "미국 국채 2년",
            "symbol": "US2YY",
            "close": "4.16",
            "chg": "0.08",
            "chg_pct": "-1.89%"
          },
          {
            "name": "미국 국채 30년",
            "symbol": "US30YY",
            "close": "4.94",
            "chg": "0.01",
            "chg_pct": "-0.20%"
          },
          {
            "name": "일본 국채 10년",
            "symbol": "JP10YY",
            "close": "2.68",
            "chg": "0.01",
            "chg_pct": "+0.22%"
          }
        ]
      }
    }
  }
}