{
  "as_of": "2026-06-11 09:30 KST",
  "sources": [
    "https://www.hankyung.com/koreamarket/news/all-news",
    "https://www.hankyung.com/globalmarket",
    "https://datacenter.hankyung.com/"
  ],
  "headline": "트럼프 \"이란 더 강하게 타격\"…나스닥 2% 급락 [뉴욕증시 브리핑]",
  "us_market_snapshot": [],
  "themes": [
    {
      "title": "트럼프 \"이란 더 강하게 타격\"…나스닥 2% 급락 [뉴욕증시 브리핑]",
      "summary": "",
      "url": "https://www.hankyung.com/article/2026061195616"
    },
    {
      "title": "인플레 꼭지? 무시된 호재…스페이스X 태풍 \"상장 후 나흘 기다려야\" [김현석의 월스트리트나우]",
      "summary": "",
      "url": "https://www.hankyung.com/article/202606119450i"
    },
    {
      "title": "\"이란 곳곳에서 폭발음\"…美, 이틀째 다수 표적 추가공습",
      "summary": "",
      "url": "https://www.hankyung.com/article/2026061195647"
    },
    {
      "title": "세계 돈줄 삼키는 AI 제국…IPO·증자·사모대출 '영끌'",
      "summary": "",
      "url": "https://www.hankyung.com/article/2026061090791"
    }
  ],
  "today_kr_focus": [
    "'네 마녀의 날' 코스피, 4% 급락해 7300선…중동 긴장 여파 (2026-06-11 09:14)",
    "코스피, 2.86% 하락 출발…7500선 아래로 (2026-06-11 09:02)",
    "\"LS일렉트릭, 수주 가이던스 상향이 가장 빠르게 확인될 것…목표가↑\"-유안타 (2026-06-11 08:45)"
  ],
  "carousel_implications": {
    "regime": "美 증시 조정 — 위험회피 분위기 (가설)",
    "axes": [
      {
        "axis": "반도체 회전축",
        "view": "美 반도체 지수 -3.57% 조정. 한국 반도체(삼성·하이닉스) 동조 가능성 큼. 저점 매수 진입 검토 — 확신은 합의 시그널과 교차검증 필요.",
        "confidence": "중 — 백테스트 미검증",
        "trigger_metric": "美 반도체 지수",
        "trigger_value": "-3.57%"
      },
      {
        "axis": "환율 민감 회전축",
        "view": "USDKRW +0.31% (원화 약세). 수출주(반도체·자동차) 마진 호조 — 단 단일 일자 변동은 노이즈 가능, 추세 확인 후 회전 검토.",
        "confidence": "낮음 — 단기 변동성 큼",
        "trigger_metric": "USDKRW",
        "trigger_value": "+0.31%"
      }
    ],
    "note": "★ 모든 함의는 미검증 가설. 백테스트 alpha 확인 전 매매 직접 사용 금지."
  },
  "macro": {
    "collected_at": "2026-06-11T09:30:47.457369+09:00",
    "source": "datacenter.hankyung.com",
    "categories": {
      "major-indices": {
        "label": "한경 데이터센터 해외지수",
        "items": [
          {
            "name": "나스닥",
            "symbol": "NASDAQ",
            "close": "25,169.50",
            "chg": "509.32",
            "chg_pct": "-1.98%"
          },
          {
            "name": "다우존스",
            "symbol": "DJIA",
            "close": "49,918.78",
            "chg": "953.33",
            "chg_pct": "-1.87%"
          },
          {
            "name": "S&P 500",
            "symbol": "SP500",
            "close": "7,266.99",
            "chg": "119.66",
            "chg_pct": "-1.62%"
          },
          {
            "name": "반도체",
            "symbol": "PSEMICON",
            "close": "12,206.46",
            "chg": "451.35",
            "chg_pct": "-3.57%"
          },
          {
            "name": "NIKKEI 225",
            "symbol": "NIKKEI",
            "close": "64,179.27",
            "chg": "1,237.36",
            "chg_pct": "-1.89%"
          },
          {
            "name": "대만",
            "symbol": "WEIGHT",
            "close": "43,225.54",
            "chg": "1,478.90",
            "chg_pct": "-3.31%"
          },
          {
            "name": "독일",
            "symbol": "DAX",
            "close": "24,195.31",
            "chg": "237.75",
            "chg_pct": "-0.97%"
          },
          {
            "name": "홍콩",
            "symbol": "HANGSE",
            "close": "24,407.96",
            "chg": "157.94",
            "chg_pct": "-0.64%"
          }
        ]
      },
      "currencies": {
        "label": "한경 데이터센터 외환",
        "items": [
          {
            "name": "미국",
            "symbol": "USDKRW",
            "close": "1,524.79",
            "chg": "4.69",
            "chg_pct": "+0.31%"
          },
          {
            "name": "유로",
            "symbol": "EURKRW",
            "close": "1,759.60",
            "chg": "3.77",
            "chg_pct": "+0.21%"
          },
          {
            "name": "일본",
            "symbol": "JPYKRW",
            "close": "949.72",
            "chg": "2.54",
            "chg_pct": "+0.27%"
          },
          {
            "name": "중국",
            "symbol": "CNYKRW",
            "close": "225.11",
            "chg": "0.68",
            "chg_pct": "+0.30%"
          }
        ]
      },
      "commodities": {
        "label": "한경 데이터센터 원자재",
        "items": [
          {
            "name": "브렌트",
            "symbol": "BRENTF",
            "close": "93.10",
            "chg": "1.65",
            "chg_pct": "+1.80%"
          },
          {
            "name": "두바이유 현물",
            "symbol": "DUBAIF",
            "close": "87.10",
            "chg": "2.49",
            "chg_pct": "-2.78%"
          },
          {
            "name": "니켈",
            "symbol": "LMENIC",
            "close": "17,380.00",
            "chg": "550.00",
            "chg_pct": "-3.07%"
          },
          {
            "name": "알루미늄 H/G 캐시",
            "symbol": "LMEALC",
            "close": "3,489.00",
            "chg": "119.00",
            "chg_pct": "-3.30%"
          },
          {
            "name": "전기동",
            "symbol": "LMECOC",
            "close": "13,370.00",
            "chg": "346.00",
            "chg_pct": "-2.52%"
          },
          {
            "name": "전기동 3M",
            "symbol": "LMECOF",
            "close": "13,431.00",
            "chg": "314.00",
            "chg_pct": "-2.28%"
          }
        ]
      },
      "rates-bonds": {
        "label": "한경 데이터센터 채권금리",
        "items": [
          {
            "name": "국고10년",
            "symbol": "KR10Y",
            "close": "4.27",
            "chg": "0.00",
            "chg_pct": "0.00%"
          },
          {
            "name": "국고3년",
            "symbol": "KR3Y",
            "close": "3.88",
            "chg": "0.03",
            "chg_pct": "+0.65%"
          },
          {
            "name": "미국 국채 10년",
            "symbol": "US10YY",
            "close": "4.55",
            "chg": "0.02",
            "chg_pct": "+0.44%"
          },
          {
            "name": "미국 국채 2년",
            "symbol": "US2YY",
            "close": "4.13",
            "chg": "0.00",
            "chg_pct": "0.00%"
          },
          {
            "name": "미국 국채 30년",
            "symbol": "US30YY",
            "close": "5.03",
            "chg": "0.02",
            "chg_pct": "+0.40%"
          },
          {
            "name": "일본 국채 10년",
            "symbol": "JP10YY",
            "close": "2.67",
            "chg": "0.05",
            "chg_pct": "-1.69%"
          }
        ]
      }
    }
  }
}